polyterm/__init__.py
polyterm/__main__.py
polyterm/api/__init__.py
polyterm/api/aggregator.py
polyterm/api/clob.py
polyterm/api/gamma.py
polyterm/api/subgraph.py
polyterm/cli/__init__.py
polyterm/cli/main.py
polyterm/cli/commands/__init__.py
polyterm/cli/commands/alertcenter.py
polyterm/cli/commands/alerts.py
polyterm/cli/commands/analytics.py
polyterm/cli/commands/arbitrage.py
polyterm/cli/commands/attribution.py
polyterm/cli/commands/backtest.py
polyterm/cli/commands/benchmark.py
polyterm/cli/commands/bookmarks.py
polyterm/cli/commands/calendar.py
polyterm/cli/commands/calibrate.py
polyterm/cli/commands/chart.py
polyterm/cli/commands/compare.py
polyterm/cli/commands/config_cmd.py
polyterm/cli/commands/correlate.py
polyterm/cli/commands/crypto15m.py
polyterm/cli/commands/dashboard.py
polyterm/cli/commands/depth.py
polyterm/cli/commands/digest.py
polyterm/cli/commands/ev.py
polyterm/cli/commands/exit.py
polyterm/cli/commands/export_cmd.py
polyterm/cli/commands/fees.py
polyterm/cli/commands/follow.py
polyterm/cli/commands/glossary.py
polyterm/cli/commands/groups.py
polyterm/cli/commands/health.py
polyterm/cli/commands/history.py
polyterm/cli/commands/hot.py
polyterm/cli/commands/journal.py
polyterm/cli/commands/ladder.py
polyterm/cli/commands/leaderboard.py
polyterm/cli/commands/liquidity.py
polyterm/cli/commands/live_monitor.py
polyterm/cli/commands/lookup.py
polyterm/cli/commands/monitor.py
polyterm/cli/commands/mywallet.py
polyterm/cli/commands/notes.py
polyterm/cli/commands/notify.py
polyterm/cli/commands/odds.py
polyterm/cli/commands/orderbook.py
polyterm/cli/commands/parlay.py
polyterm/cli/commands/pin.py
polyterm/cli/commands/pnl.py
polyterm/cli/commands/portfolio.py
polyterm/cli/commands/position.py
polyterm/cli/commands/predict.py
polyterm/cli/commands/presets.py
polyterm/cli/commands/pricealert.py
polyterm/cli/commands/quick.py
polyterm/cli/commands/quicktrade.py
polyterm/cli/commands/recent.py
polyterm/cli/commands/replay.py
polyterm-0.6.2.dist-info/licenses/LICENSE
polyterm-0.6.2.dist-info/METADATA
polyterm-0.6.2.dist-info/WHEEL
polyterm-0.6.2.dist-info/entry_points.txt
polyterm-0.6.2.dist-info/top_level.txt
polyterm-0.6.2.dist-info/RECORD
