Metadata-Version: 2.4
Name: polyterm
Version: 0.6.2
Summary: A terminal-based monitoring app for PolyMarket shifts
Home-page: https://github.com/NYTEMODEONLY/polyterm
Author: PolyTerm Contributors
Classifier: Development Status :: 3 - Alpha
Classifier: Intended Audience :: Developers
Classifier: Topic :: Software Development :: Libraries :: Python Modules
Classifier: License :: OSI Approved :: MIT License
Classifier: Programming Language :: Python :: 3
Classifier: Programming Language :: Python :: 3.8
Classifier: Programming Language :: Python :: 3.9
Classifier: Programming Language :: Python :: 3.10
Classifier: Programming Language :: Python :: 3.11
Classifier: Operating System :: OS Independent
Requires-Python: >=3.8
License-File: LICENSE
Requires-Dist: requests>=2.31.0
Requires-Dist: aiohttp>=3.9.0
Requires-Dist: websockets>=12.0
Requires-Dist: gql[all]>=3.5.0
Requires-Dist: click>=8.1.7
Requires-Dist: typer>=0.9.0
Requires-Dist: rich>=13.7.0
Requires-Dist: toml>=0.10.2
Requires-Dist: pandas>=2.1.0
Requires-Dist: python-dateutil>=2.8.2
Requires-Dist: packaging>=23.0
Requires-Dist: pytest>=7.4.3
Requires-Dist: pytest-asyncio>=0.21.1
Requires-Dist: pytest-mock>=3.12.0
Requires-Dist: responses>=0.24.1
Requires-Dist: plyer>=2.1.0
Dynamic: author
Dynamic: classifier
Dynamic: description
Dynamic: description-content-type
Dynamic: home-page
Dynamic: license-file
Dynamic: requires-dist
Dynamic: requires-python
Dynamic: summary
